[{"image":"https:\/\/scontent-mad1-1.cdninstagram.com\/v\/t51.2885-15\/e35\/p1080x1080\/125204067_1002598870224938_1060529798565811272_n.jpg?_nc_ht=scontent-mad1-1.cdninstagram.com&_nc_cat=1&_nc_ohc=pkdL4Wqz7gMAX8O0SHX&tp=19&oh=fe83e07b030fbcf75b662e120f901085&oe=5FB297A9","link":"https:\/\/www.instagram.com\/p\/CHjqO77jx6F\/","timestamp":1605326873,"thumb":"https:\/\/scontent-mad1-1.cdninstagram.com\/v\/t51.2885-15\/sh0.08\/e35\/c0.481.1240.1240a\/s640x640\/125204067_1002598870224938_1060529798565811272_n.jpg?_nc_ht=scontent-mad1-1.cdninstagram.com&_nc_cat=1&_nc_ohc=pkdL4Wqz7gMAX8O0SHX&_nc_tp=24&oh=a83dcd68689a0cc2d59c604682c16751&oe=5FB259C4","caption":"This weekend, we celebrate Diwali \ud83e\ude94 \ud83c\udf87 with Agasthya Shah (@agasthya.shah), a comedy creator from Mumbai, India.\u2063\n\u2063\n\u201cMy most favorite thing about Diwali is that it brings my entire family together to celebrate festivities,\u201d says the 18-year-old. \u201cDressing up in traditional wear and the lavish spread of food on the Diwali day is an added bonus.\u201d\u2063\n\u2063\nThe festival of lights celebrated by South Asian communities around the world is a time for new beginnings, light over darkness and spreading joy, something that Agasthya gets from his family every day.\u2063\n\u2063\n\u201cThey are my number one support system, and they encourage me because they know that creating videos will uplift my mood in a jiffy,\u201d he says. #ShareYourLight\u2063\n\u2063\nReel by @agasthya.shah","alt":""},{"image":"https:\/\/scontent-mad1-1.cdninstagram.com\/v\/t51.2885-15\/e35\/p1080x1080\/125109071_364493854641586_2258932578478109744_n.jpg?_nc_ht=scontent-mad1-1.cdninstagram.com&_nc_cat=1&_nc_ohc=xQSTlJSa0rAAX_tdNZv&tp=19&oh=56d12584b51235926d925fb3eb4741a3&oe=5FDBB67B","link":"https:\/\/www.instagram.com\/p\/CHjBn1fs9k0\/","timestamp":1605305569,"thumb":"https:\/\/scontent-mad1-1.cdninstagram.com\/v\/t51.2885-15\/sh0.08\/e35\/c0.166.1346.1346a\/s640x640\/125109071_364493854641586_2258932578478109744_n.jpg?_nc_ht=scontent-mad1-1.cdninstagram.com&_nc_cat=1&_nc_ohc=xQSTlJSa0rAAX_tdNZv&_nc_tp=24&oh=af8aefab30e683cdd0e7d6d59b1286b8&oe=5FD86D19","caption":"On today\u2019s #WeeklyFluff, we\u2019re hopping around town with Kumagoro (@kuma.goro), an easygoing Netherland dwarf rabbit who loves a good outdoor adventure.\u2063\n\u2063\nPhoto by @kuma.goro","alt":"A light brown rabbit is held in front of pink flowers."},{"image":"https:\/\/scontent-mad1-1.cdninstagram.com\/v\/t51.2885-15\/e35\/124827067_125890269070150_641476707169884631_n.jpg?_nc_ht=scontent-mad1-1.cdninstagram.com&_nc_cat=1&_nc_ohc=ljO5LUE9RvQAX9fipGV&tp=18&oh=6a34f78af4197bc8919aa6aff7bf1d18&oe=5FB2F2B3","link":"https:\/\/www.instagram.com\/p\/CHix8aijVbJ\/","timestamp":1605297359,"thumb":"https:\/\/scontent-mad1-1.cdninstagram.com\/v\/t51.2885-15\/sh0.08\/e35\/c0.280.720.720a\/s640x640\/124827067_125890269070150_641476707169884631_n.jpg?_nc_ht=scontent-mad1-1.cdninstagram.com&_nc_cat=1&_nc_ohc=ljO5LUE9RvQAX9fipGV&_nc_tp=24&oh=d1e219a52dfb0956c020adc0fa86a720&oe=5FB2DF44","caption":"Jump through hoops, then dance through \u2018em. Amirite, Ari? \ud83e\udd38\u200d\u2640\ufe0f\ud83d\ude43\u2063\n\u2063\nCheck out our story right now to see more things that made us jump with joy this week.\u2063\n\u2063\nReel by @elena_shinohara; Music by @arianagrande \u2063","alt":""},{"image":"https:\/\/scontent-mad1-1.cdninstagram.com\/v\/t51.2885-15\/e35\/p1080x1080\/124467103_180877100342960_6482657917052585598_n.jpg?_nc_ht=scontent-mad1-1.cdninstagram.com&_nc_cat=1&_nc_ohc=JVwr0XLUYCIAX-KAN32&tp=19&oh=90f588e2051617724969e6cd7b589a7a&oe=5FDB39AC","link":"https:\/\/www.instagram.com\/p\/CHf5trlM_RJ\/","timestamp":1605200760,"thumb":"https:\/\/scontent-mad1-1.cdninstagram.com\/v\/t51.2885-15\/sh0.08\/e35\/c0.180.1440.1440a\/s640x640\/124467103_180877100342960_6482657917052585598_n.jpg?_nc_ht=scontent-mad1-1.cdninstagram.com&_nc_cat=1&_nc_ohc=JVwr0XLUYCIAX-KAN32&_nc_tp=24&oh=f60fc14fea5ba7bc42d3a0b4cc9f4993&oe=5FD99090","caption":"Today we\u2019re announcing some exciting changes to Instagram \u2014 a Shop tab, a Reels tab and more people having access to the new @messenger experience on Instagram.\u2063\n\u2063\nThe Shop tab gives you a better way to connect with brands and creators and discover products you love. With the new tab, we\u2019re making it easy to get inspired by creators you love, shop on Instagram and support small businesses. You can find personalized recommendations, editors\u2019 picks curated by our @shop channel, shoppable videos, new product collections and more.\u2063\n\ud83c\udf1f\u2063\nWe first launched Reels a few months ago, and now we\u2019re rolling out the Reels tab to be a kind of stage, a place where people can share their creativity with the world and get a chance to break out and find an audience. The Reels tab makes it easier for you to discover short, fun videos from creators all over the world and people just like you.\u2063\n\ud83c\udf1f\u2063\nAs we announced in September, we\u2019re continuing to roll out an update that will be available to your Instagram DMs \u2014 a new Messenger experience on the app. By connecting the Messenger and Instagram experience, we\u2019re able to bring some of the best Messenger features to Instagram, so you have access to the best messaging experience, no matter which app you use. \u2063\n\ud83c\udf1f\u2063\n\u2063\nWe\u2019re excited about these changes and believe it gives Instagram a much-needed refresh. Learn more about all these changes from the link in our bio. \u2764\ufe0f","alt":"Graphic of Shop logo."},{"image":"https:\/\/scontent-mad1-1.cdninstagram.com\/v\/t51.2885-15\/e35\/p1080x1080\/124372782_404101680973676_7356675722273924471_n.jpg?_nc_ht=scontent-mad1-1.cdninstagram.com&_nc_cat=1&_nc_ohc=29zjIwbSx0EAX_Fr2Fg&tp=19&oh=55abd21bb48d8a66eb5d4dcd0c94057e&oe=5FDBB446","link":"https:\/\/www.instagram.com\/p\/CHdjJ0yM3eB\/","timestamp":1605121823,"thumb":"https:\/\/scontent-mad1-1.cdninstagram.com\/v\/t51.2885-15\/sh0.08\/e35\/c0.168.1348.1348a\/s640x640\/124372782_404101680973676_7356675722273924471_n.jpg?_nc_ht=scontent-mad1-1.cdninstagram.com&_nc_cat=1&_nc_ohc=29zjIwbSx0EAX_Fr2Fg&_nc_tp=24&oh=02bb6e1e1a13c36192448c67120d2886&oe=5FD97482","caption":"This year, German creator and author Diana zur L\u00f6wen (@dianazurloewen) focused on her personal well-being. For Diana, that means not criticizing and comparing herself to others while using her platform to spread important messages. \ud83d\udc9e\u2063\n\u2063\n\u201cI can\u2019t please everyone and today it\u2019s more important to me to address topics people may feel uncomfortable with in order to to help others,\u201d she says.\u2063\n\u2063\nThrough work with @bravomagazin and the nonprofit @juuuport, Diana is encouraging others to #stayreal and let go of the pressure to be perfect. \u2063\n\u2063\n\u201cStop thinking you are not good enough,\u201d says Diana. \u201cInstead of doubting your decisions, learn to become your own cheerleader and keep motivating yourself even through hard times.\u201d \u2728\ud83c\udf37\u2728\ud83c\udf37\u2063\n\u2063\nPhoto by @dianazurloewen","alt":"A woman sits on a sidewalk holding a small white dog."},{"image":"https:\/\/scontent-mad1-1.cdninstagram.com\/v\/t51.2885-15\/e35\/124365997_362252511558615_5221754059975270771_n.jpg?_nc_ht=scontent-mad1-1.cdninstagram.com&_nc_cat=1&_nc_ohc=gJn__nduY34AX_H3Xct&tp=18&oh=439f0119c7789ab94f8cb5e76f63414b&oe=5FB2A88E","link":"https:\/\/www.instagram.com\/p\/CHdVpHLsNpJ\/","timestamp":1605114739,"thumb":"https:\/\/scontent-mad1-1.cdninstagram.com\/v\/t51.2885-15\/sh0.08\/e35\/c0.90.720.720a\/s640x640\/124365997_362252511558615_5221754059975270771_n.jpg?_nc_ht=scontent-mad1-1.cdninstagram.com&_nc_cat=1&_nc_ohc=gJn__nduY34AX_H3Xct&_nc_tp=24&oh=f631d4e0ef4124b931da991af6524242&oe=5FB29EE1","caption":"Designer Nathan Riley\u2019s (@nrlyco) calming 3D digital environments offer an escape from the real world by creating virtual ones full of possibility. His dreamy locations sit on the border between photo-realism and stylized 3D, often incorporating satisfying movement.\u2063\n\u2063\n\u201cI seem to gravitate towards images that blur the lines of reality and fantasy. I enjoy creating visuals that you can picture yourself in but on closer inspection have an element of surrealism that makes you question it,\u201d he says.\u2063\n\u2063\n\u201cHaving your world restricted and drastically reduced in scale can do strange things to your creative process. The physical restrictions of not being able to go out and explore in the real world make me more inspired to create and design in virtual worlds.\u2063\n\u2063\nI think the most interesting part of these images is that they are a reflection of how I was feeling at the time \u2014 confined and dreaming of an escape, but also the literal reflections created in the scenes.\u201d\u2063\n\u2063\n#ThisWeekOnInstagram\u2063\n\u2063\nVideos by @nrlyco","alt":""}]